agora/__init__.py
agora/abc.py
agora/io/__init__.py
agora/io/bridge.py
agora/io/cells.py
agora/io/metadata.py
agora/io/reader.py
agora/io/signal.py
agora/io/utils.py
agora/io/writer.py
agora/utils/__init__.py
agora/utils/example.py
agora/utils/lineage.py
agora/utils/server_info
logfile_parser/README.md
logfile_parser/__init__.py
logfile_parser/grammars/cExperiment_log_format.json
logfile_parser/grammars/multiDGUI_acq_format.json
logfile_parser/grammars/multiDGUI_log_format.json
logfile_parser/logfile_parser.py
aliby_agora-0.2.33.dist-info/LICENSE
aliby_agora-0.2.33.dist-info/WHEEL
aliby_agora-0.2.33.dist-info/METADATA
aliby_agora-0.2.33.dist-info/RECORD
