Metadata-Version: 2.1
Name: aliby-agora
Version: 0.2.33
Summary: A gathering of shared utilities for the Swain Lab image processing pipeline.
License: MIT
Author: Alán Muñoz
Author-email: amuoz@ed.ac.uk
Requires-Python: >=3.7.1,<3.11
Classifier: License :: OSI Approved :: MIT License
Classifier: Programming Language :: Python :: 3
Classifier: Programming Language :: Python :: 3.10
Classifier: Programming Language :: Python :: 3.8
Classifier: Programming Language :: Python :: 3.9
Requires-Dist: PyYAML (>=6.0,<7.0)
Requires-Dist: h5py (==2.10)
Requires-Dist: numpy (==1.21.6)
Requires-Dist: opencv-python
Requires-Dist: pandas (==1.3.3)
Requires-Dist: py-find-1st (>=1.1.5,<2.0.0)
Requires-Dist: scipy (>=1.7.3)
